LICENSE
README.md
gtfs/__init__.py
gtfs/admin.py
gtfs/apps.py
gtfs/fields.py
gtfs/models.py
gtfs/urls.py
gtfs/views.py
gtfs/management/__init__.py
gtfs/management/commands/importgtfs.py
gtfs/utils/__init__.py
gtfs/utils/realtime.py
gtfs/utils/schedule.py
gtfs/utils/stop_times.py
gtfs_django-0.1.0.dist-info/METADATA
gtfs_django-0.1.0.dist-info/WHEEL
gtfs_django-0.1.0.dist-info/licenses/LICENSE
gtfs_django-0.1.0.dist-info/RECORD
