Metadata-Version: 2.4
Name: gtfs-django
Version: 0.1.0
Summary: A Django app for processing and managing GTFS (General Transit Feed Specification) data
Project-URL: Homepage, https://github.com/simovilab/gtfs-django
Project-URL: Repository, https://github.com/simovilab/gtfs-django.git
Project-URL: Issues, https://github.com/simovilab/gtfs-django/issues
License: Apache-2.0
License-File: LICENSE
Keywords: django,geodjango,gtfs,postgis,realtime,transit
Requires-Python: >=3.12
Requires-Dist: django>=5.2.0
Requires-Dist: gtfs-realtime-bindings>=1.0.0
Requires-Dist: protobuf>=6.32.1
Requires-Dist: requests>=2.32.5
Provides-Extra: postgresql
Requires-Dist: psycopg2-binary>=2.9.10; extra == 'postgresql'
